<annotation>
	<folder>Yes</folder>
	<filename>Yes.a43ee2b2-60e4-11ec-bc5b-5cfb3a0e6dd8.jpg</filename>
	<path>C:\Users\taran\RealTimeObjectDetection\Tensorflow\workspace\images\collectedimages\Yes\Yes.a43ee2b2-60e4-11ec-bc5b-5cfb3a0e6dd8.jpg</path>
	<source>
		<database>Unknown</database>
	</source>
	<size>
		<width>640</width>
		<height>480</height>
		<depth>3</depth>
	</size>
	<segmented>0</segmented>
	<object>
		<name>Yes</name>
		<pose>Unspecified</pose>
		<truncated>0</truncated>
		<difficult>0</difficult>
		<bndbox>
			<xmin>439</xmin>
			<ymin>152</ymin>
			<xmax>571</xmax>
			<ymax>262</ymax>
		</bndbox>
	</object>
</annotation>
